{
  "name": "Martin Bachvarov",
  "jobTitle": "QA Master Engineer",
  "bio": "Lorem...",
  "from": "Bulgaria",
  "lives": "United Kingdom",
  "bornIn": "1988",
  "gender": "M",
  "skills": {
    "colOne": [
      {
        "name": "JavaScript",
        "progress": "45%"
      },
      {
        "name": "PHP",
        "progress": "24%"
      },
      {
        "name": "Python",
        "progress": "50%"
      },
      {
        "name": "JAVA",
        "progress": "79%"
      },
      {
        "name": "ReactJS",
        "progress": "36%"
      },
      {
        "name": "Figma",
        "progress": "69%"
      }
    ]
  },
  "education": [
    {
      "year": "2016",
      "degree": "ISTQB foundation level certificate",
      "school": "UDEMY",
      "text": "Lorem..."
    },
    {
      "year": "2013",
      "degree": "Physiotherapy bachelor degree",
      "school": "Medical University of Sofia, Bulgaria",
      "text": "Lorem..."
    },
    {
      "year": "2007",
      "degree": "High-School diploma",
      "school": "Jordan Jovkov high school of Tutrakan",
      "text": "Lorem..."
    }
  ],
  "experience": [
    {
      "year": "2019 - Current",
      "title": "QA: Rank Automation Engineer",
      "company": "Tandem Bank",
      "text": "Lorem..."
    },
    {
      "year": "2017",
      "title": "QA: Rank Manual Tester",
      "company": "ZIBID Ltd",
      "text": "Lorem ..."
    }

  ]
}